tiny_tf/__init__.py
tiny_tf/test.py
tiny_tf/tf.py
tiny_tf/transformations.py
tiny_tf-1.2.0.dist-info/LICENSE
tiny_tf-1.2.0.dist-info/METADATA
tiny_tf-1.2.0.dist-info/WHEEL
tiny_tf-1.2.0.dist-info/top_level.txt
tiny_tf-1.2.0.dist-info/RECORD
