Metadata-Version: 2.1
Name: tiny-tf
Version: 1.2.0
Summary: Shameless reimplementation of some parts of the API from Tully Foote's TF library
Home-page: UNKNOWN
Author: Jariullah Safi
Author-email: safijari@isu.edu
License: UNKNOWN
Platform: UNKNOWN
License-File: LICENSE
Requires-Dist: numpy
